{
  "generatedAt": "2026-06-18T15:33:06.242Z",
  "username": "AdrianIp",
  "profileFetchedAt": "2026-06-18T15:31:01.839Z",
  "publicAcceptedSolved": 294,
  "publicAcceptedSubmissions": 333,
  "publicAttemptedProblems": 295,
  "publicTotalSubmissions": 410,
  "localProblemFolders": 295,
  "localCanonicalSolutions": 226,
  "estimatedSolvedGap": 0,
  "status": "ok",
  "knownLocalProblems": [
    {
      "folder": "0001-two-sum",
      "slug": "two-sum",
      "hasCanonicalSolution": true
    },
    {
      "folder": "0002-add-two-numbers",
      "slug": "add-two-numbers",
      "hasCanonicalSolution": true
    },
    {
      "folder": "0003-longest-substring-without-repeating-characters",
      "slug": "longest-substring-without-repeating-characters",
      "hasCanonicalSolution": true
    },
    {
      "folder": "0004-median-of-two-sorted-arrays",
      "slug": "median-of-two-sorted-arrays",
      "hasCanonicalSolution": true
    },
    {
      "folder": "0005-longest-palindromic-substring",
      "slug": "longest-palindromic-substring",
      "hasCanonicalSolution": true
    },
    {
      "folder": "0006-zigzag-conversion",
      "slug": "zigzag-conversion",
      "hasCanonicalSolution": true
    },
    {
      "folder": "0007-reverse-integer",
      "slug": "reverse-integer",
      "hasCanonicalSolution": true
    },
    {
      "folder": "0009-palindrome-number",
      "slug": "palindrome-number",
      "hasCanonicalSolution": true
    },
    {
      "folder": "0011-container-with-most-water",
      "slug": "container-with-most-water",
      "hasCanonicalSolution": true
    },
    {
      "folder": "0012-integer-to-roman",
      "slug": "integer-to-roman",
      "hasCanonicalSolution": true
    },
    {
      "folder": "0013-roman-to-integer",
      "slug": "roman-to-integer",
      "hasCanonicalSolution": true
    },
    {
      "folder": "0014-longest-common-prefix",
      "slug": "longest-common-prefix",
      "hasCanonicalSolution": true
    },
    {
      "folder": "0015-3sum",
      "slug": "3sum",
      "hasCanonicalSolution": true
    },
    {
      "folder": "0020-valid-parentheses",
      "slug": "valid-parentheses",
      "hasCanonicalSolution": true
    },
    {
      "folder": "0021-merge-two-sorted-lists",
      "slug": "merge-two-sorted-lists",
      "hasCanonicalSolution": true
    },
    {
      "folder": "0026-remove-duplicates-from-sorted-array",
      "slug": "remove-duplicates-from-sorted-array",
      "hasCanonicalSolution": true
    },
    {
      "folder": "0028-find-the-index-of-the-first-occurrence-in-a-string",
      "slug": "find-the-index-of-the-first-occurrence-in-a-string",
      "hasCanonicalSolution": true
    },
    {
      "folder": "0029-divide-two-integers",
      "slug": "divide-two-integers",
      "hasCanonicalSolution": true
    },
    {
      "folder": "0035-search-insert-position",
      "slug": "search-insert-position",
      "hasCanonicalSolution": false
    },
    {
      "folder": "0046-permutations",
      "slug": "permutations",
      "hasCanonicalSolution": false
    },
    {
      "folder": "0049-group-anagrams",
      "slug": "group-anagrams",
      "hasCanonicalSolution": true
    },
    {
      "folder": "0050-powx-n",
      "slug": "powx-n",
      "hasCanonicalSolution": false
    },
    {
      "folder": "0058-length-of-last-word",
      "slug": "length-of-last-word",
      "hasCanonicalSolution": true
    },
    {
      "folder": "0060-permutation-sequence",
      "slug": "permutation-sequence",
      "hasCanonicalSolution": true
    },
    {
      "folder": "0066-plus-one",
      "slug": "plus-one",
      "hasCanonicalSolution": true
    },
    {
      "folder": "0069-sqrtx",
      "slug": "sqrtx",
      "hasCanonicalSolution": true
    },
    {
      "folder": "0070-climbing-stairs",
      "slug": "climbing-stairs",
      "hasCanonicalSolution": true
    },
    {
      "folder": "0083-remove-duplicates-from-sorted-list",
      "slug": "remove-duplicates-from-sorted-list",
      "hasCanonicalSolution": true
    },
    {
      "folder": "0118-pascals-triangle",
      "slug": "pascals-triangle",
      "hasCanonicalSolution": true
    },
    {
      "folder": "0121-best-time-to-buy-and-sell-stock",
      "slug": "best-time-to-buy-and-sell-stock",
      "hasCanonicalSolution": true
    },
    {
      "folder": "0125-valid-palindrome",
      "slug": "valid-palindrome",
      "hasCanonicalSolution": true
    },
    {
      "folder": "0128-longest-consecutive-sequence",
      "slug": "longest-consecutive-sequence",
      "hasCanonicalSolution": true
    },
    {
      "folder": "0136-single-number",
      "slug": "single-number",
      "hasCanonicalSolution": true
    },
    {
      "folder": "0151-reverse-words-in-a-string",
      "slug": "reverse-words-in-a-string",
      "hasCanonicalSolution": true
    },
    {
      "folder": "0167-two-sum-ii-input-array-is-sorted",
      "slug": "two-sum-ii-input-array-is-sorted",
      "hasCanonicalSolution": true
    },
    {
      "folder": "0168-excel-sheet-column-title",
      "slug": "excel-sheet-column-title",
      "hasCanonicalSolution": true
    },
    {
      "folder": "0171-excel-sheet-column-number",
      "slug": "excel-sheet-column-number",
      "hasCanonicalSolution": true
    },
    {
      "folder": "0172-factorial-trailing-zeroes",
      "slug": "factorial-trailing-zeroes",
      "hasCanonicalSolution": true
    },
    {
      "folder": "0175-combine-two-tables",
      "slug": "combine-two-tables",
      "hasCanonicalSolution": true
    },
    {
      "folder": "0181-employees-earning-more-than-their-managers",
      "slug": "employees-earning-more-than-their-managers",
      "hasCanonicalSolution": true
    },
    {
      "folder": "0189-rotate-array",
      "slug": "rotate-array",
      "hasCanonicalSolution": false
    },
    {
      "folder": "0190-reverse-bits",
      "slug": "reverse-bits",
      "hasCanonicalSolution": true
    },
    {
      "folder": "0191-number-of-1-bits",
      "slug": "number-of-1-bits",
      "hasCanonicalSolution": false
    },
    {
      "folder": "0204-count-primes",
      "slug": "count-primes",
      "hasCanonicalSolution": true
    },
    {
      "folder": "0205-isomorphic-strings",
      "slug": "isomorphic-strings",
      "hasCanonicalSolution": true
    },
    {
      "folder": "0206-reverse-linked-list",
      "slug": "reverse-linked-list",
      "hasCanonicalSolution": true
    },
    {
      "folder": "0217-contains-duplicate",
      "slug": "contains-duplicate",
      "hasCanonicalSolution": true
    },
    {
      "folder": "0219-contains-duplicate-ii",
      "slug": "contains-duplicate-ii",
      "hasCanonicalSolution": true
    },
    {
      "folder": "0224-basic-calculator",
      "slug": "basic-calculator",
      "hasCanonicalSolution": false
    },
    {
      "folder": "0231-power-of-two",
      "slug": "power-of-two",
      "hasCanonicalSolution": false
    },
    {
      "folder": "0234-palindrome-linked-list",
      "slug": "palindrome-linked-list",
      "hasCanonicalSolution": true
    },
    {
      "folder": "0238-product-of-array-except-self",
      "slug": "product-of-array-except-self",
      "hasCanonicalSolution": true
    },
    {
      "folder": "0242-valid-anagram",
      "slug": "valid-anagram",
      "hasCanonicalSolution": true
    },
    {
      "folder": "0258-add-digits",
      "slug": "add-digits",
      "hasCanonicalSolution": true
    },
    {
      "folder": "0263-ugly-number",
      "slug": "ugly-number",
      "hasCanonicalSolution": true
    },
    {
      "folder": "0268-missing-number",
      "slug": "missing-number",
      "hasCanonicalSolution": true
    },
    {
      "folder": "0283-move-zeroes",
      "slug": "move-zeroes",
      "hasCanonicalSolution": true
    },
    {
      "folder": "0292-nim-game",
      "slug": "nim-game",
      "hasCanonicalSolution": true
    },
    {
      "folder": "0326-power-of-three",
      "slug": "power-of-three",
      "hasCanonicalSolution": false
    },
    {
      "folder": "0342-power-of-four",
      "slug": "power-of-four",
      "hasCanonicalSolution": true
    },
    {
      "folder": "0344-reverse-string",
      "slug": "reverse-string",
      "hasCanonicalSolution": true
    },
    {
      "folder": "0345-reverse-vowels-of-a-string",
      "slug": "reverse-vowels-of-a-string",
      "hasCanonicalSolution": true
    },
    {
      "folder": "0347-top-k-frequent-elements",
      "slug": "top-k-frequent-elements",
      "hasCanonicalSolution": true
    },
    {
      "folder": "0349-intersection-of-two-arrays",
      "slug": "intersection-of-two-arrays",
      "hasCanonicalSolution": true
    },
    {
      "folder": "0350-intersection-of-two-arrays-ii",
      "slug": "intersection-of-two-arrays-ii",
      "hasCanonicalSolution": true
    },
    {
      "folder": "0367-valid-perfect-square",
      "slug": "valid-perfect-square",
      "hasCanonicalSolution": false
    },
    {
      "folder": "0383-ransom-note",
      "slug": "ransom-note",
      "hasCanonicalSolution": false
    },
    {
      "folder": "0387-first-unique-character-in-a-string",
      "slug": "first-unique-character-in-a-string",
      "hasCanonicalSolution": true
    },
    {
      "folder": "0389-find-the-difference",
      "slug": "find-the-difference",
      "hasCanonicalSolution": true
    },
    {
      "folder": "0409-longest-palindrome",
      "slug": "longest-palindrome",
      "hasCanonicalSolution": true
    },
    {
      "folder": "0412-fizz-buzz",
      "slug": "fizz-buzz",
      "hasCanonicalSolution": true
    },
    {
      "folder": "0413-arithmetic-slices",
      "slug": "arithmetic-slices",
      "hasCanonicalSolution": true
    },
    {
      "folder": "0414-third-maximum-number",
      "slug": "third-maximum-number",
      "hasCanonicalSolution": true
    },
    {
      "folder": "0441-arranging-coins",
      "slug": "arranging-coins",
      "hasCanonicalSolution": false
    },
    {
      "folder": "0442-find-all-duplicates-in-an-array",
      "slug": "find-all-duplicates-in-an-array",
      "hasCanonicalSolution": false
    },
    {
      "folder": "0448-find-all-numbers-disappeared-in-an-array",
      "slug": "find-all-numbers-disappeared-in-an-array",
      "hasCanonicalSolution": true
    },
    {
      "folder": "0451-sort-characters-by-frequency",
      "slug": "sort-characters-by-frequency",
      "hasCanonicalSolution": true
    },
    {
      "folder": "0485-max-consecutive-ones",
      "slug": "max-consecutive-ones",
      "hasCanonicalSolution": true
    },
    {
      "folder": "0507-perfect-number",
      "slug": "perfect-number",
      "hasCanonicalSolution": true
    },
    {
      "folder": "0509-fibonacci-number",
      "slug": "fibonacci-number",
      "hasCanonicalSolution": true
    },
    {
      "folder": "0520-detect-capital",
      "slug": "detect-capital",
      "hasCanonicalSolution": true
    },
    {
      "folder": "0551-student-attendance-record-i",
      "slug": "student-attendance-record-i",
      "hasCanonicalSolution": true
    },
    {
      "folder": "0557-reverse-words-in-a-string-iii",
      "slug": "reverse-words-in-a-string-iii",
      "hasCanonicalSolution": false
    },
    {
      "folder": "0561-array-partition",
      "slug": "array-partition",
      "hasCanonicalSolution": true
    },
    {
      "folder": "0605-can-place-flowers",
      "slug": "can-place-flowers",
      "hasCanonicalSolution": true
    },
    {
      "folder": "0628-maximum-product-of-three-numbers",
      "slug": "maximum-product-of-three-numbers",
      "hasCanonicalSolution": true
    },
    {
      "folder": "0645-set-mismatch",
      "slug": "set-mismatch",
      "hasCanonicalSolution": true
    },
    {
      "folder": "0657-robot-return-to-origin",
      "slug": "robot-return-to-origin",
      "hasCanonicalSolution": true
    },
    {
      "folder": "0682-baseball-game",
      "slug": "baseball-game",
      "hasCanonicalSolution": true
    },
    {
      "folder": "0692-top-k-frequent-words",
      "slug": "top-k-frequent-words",
      "hasCanonicalSolution": true
    },
    {
      "folder": "0704-binary-search",
      "slug": "binary-search",
      "hasCanonicalSolution": false
    },
    {
      "folder": "0709-to-lower-case",
      "slug": "to-lower-case",
      "hasCanonicalSolution": true
    },
    {
      "folder": "0728-self-dividing-numbers",
      "slug": "self-dividing-numbers",
      "hasCanonicalSolution": true
    },
    {
      "folder": "0744-find-smallest-letter-greater-than-target",
      "slug": "find-smallest-letter-greater-than-target",
      "hasCanonicalSolution": false
    },
    {
      "folder": "0747-largest-number-at-least-twice-of-others",
      "slug": "largest-number-at-least-twice-of-others",
      "hasCanonicalSolution": true
    },
    {
      "folder": "0771-jewels-and-stones",
      "slug": "jewels-and-stones",
      "hasCanonicalSolution": true
    },
    {
      "folder": "0804-unique-morse-code-words",
      "slug": "unique-morse-code-words",
      "hasCanonicalSolution": false
    },
    {
      "folder": "0819-most-common-word",
      "slug": "most-common-word",
      "hasCanonicalSolution": true
    },
    {
      "folder": "0867-transpose-matrix",
      "slug": "transpose-matrix",
      "hasCanonicalSolution": true
    },
    {
      "folder": "0884-uncommon-words-from-two-sentences",
      "slug": "uncommon-words-from-two-sentences",
      "hasCanonicalSolution": true
    },
    {
      "folder": "0896-monotonic-array",
      "slug": "monotonic-array",
      "hasCanonicalSolution": true
    },
    {
      "folder": "0917-reverse-only-letters",
      "slug": "reverse-only-letters",
      "hasCanonicalSolution": true
    },
    {
      "folder": "0932-beautiful-array",
      "slug": "beautiful-array",
      "hasCanonicalSolution": true
    },
    {
      "folder": "0942-di-string-match",
      "slug": "di-string-match",
      "hasCanonicalSolution": true
    },
    {
      "folder": "0977-squares-of-a-sorted-array",
      "slug": "squares-of-a-sorted-array",
      "hasCanonicalSolution": true
    },
    {
      "folder": "0989-add-to-array-form-of-integer",
      "slug": "add-to-array-form-of-integer",
      "hasCanonicalSolution": true
    },
    {
      "folder": "1002-find-common-characters",
      "slug": "find-common-characters",
      "hasCanonicalSolution": true
    },
    {
      "folder": "1015-smallest-integer-divisible-by-k",
      "slug": "smallest-integer-divisible-by-k",
      "hasCanonicalSolution": true
    },
    {
      "folder": "1021-remove-outermost-parentheses",
      "slug": "remove-outermost-parentheses",
      "hasCanonicalSolution": true
    },
    {
      "folder": "1025-divisor-game",
      "slug": "divisor-game",
      "hasCanonicalSolution": true
    },
    {
      "folder": "1037-valid-boomerang",
      "slug": "valid-boomerang",
      "hasCanonicalSolution": true
    },
    {
      "folder": "1046-last-stone-weight",
      "slug": "last-stone-weight",
      "hasCanonicalSolution": true
    },
    {
      "folder": "1051-height-checker",
      "slug": "height-checker",
      "hasCanonicalSolution": true
    },
    {
      "folder": "1071-greatest-common-divisor-of-strings",
      "slug": "greatest-common-divisor-of-strings",
      "hasCanonicalSolution": true
    },
    {
      "folder": "1108-defanging-an-ip-address",
      "slug": "defanging-an-ip-address",
      "hasCanonicalSolution": true
    },
    {
      "folder": "1207-unique-number-of-occurrences",
      "slug": "unique-number-of-occurrences",
      "hasCanonicalSolution": false
    },
    {
      "folder": "1221-split-a-string-in-balanced-strings",
      "slug": "split-a-string-in-balanced-strings",
      "hasCanonicalSolution": true
    },
    {
      "folder": "1224-maximum-equal-frequency",
      "slug": "maximum-equal-frequency",
      "hasCanonicalSolution": true
    },
    {
      "folder": "1281-subtract-the-product-and-sum-of-digits-of-an-integer",
      "slug": "subtract-the-product-and-sum-of-digits-of-an-integer",
      "hasCanonicalSolution": true
    },
    {
      "folder": "1295-find-numbers-with-even-number-of-digits",
      "slug": "find-numbers-with-even-number-of-digits",
      "hasCanonicalSolution": true
    },
    {
      "folder": "1304-find-n-unique-integers-sum-up-to-zero",
      "slug": "find-n-unique-integers-sum-up-to-zero",
      "hasCanonicalSolution": true
    },
    {
      "folder": "1323-maximum-69-number",
      "slug": "maximum-69-number",
      "hasCanonicalSolution": true
    },
    {
      "folder": "1344-angle-between-hands-of-a-clock",
      "slug": "angle-between-hands-of-a-clock",
      "hasCanonicalSolution": false
    },
    {
      "folder": "1365-how-many-numbers-are-smaller-than-the-current-number",
      "slug": "how-many-numbers-are-smaller-than-the-current-number",
      "hasCanonicalSolution": true
    },
    {
      "folder": "1374-generate-a-string-with-characters-that-have-odd-counts",
      "slug": "generate-a-string-with-characters-that-have-odd-counts",
      "hasCanonicalSolution": false
    },
    {
      "folder": "1399-count-largest-group",
      "slug": "count-largest-group",
      "hasCanonicalSolution": false
    },
    {
      "folder": "1408-string-matching-in-an-array",
      "slug": "string-matching-in-an-array",
      "hasCanonicalSolution": true
    },
    {
      "folder": "1431-kids-with-the-greatest-number-of-candies",
      "slug": "kids-with-the-greatest-number-of-candies",
      "hasCanonicalSolution": true
    },
    {
      "folder": "1436-destination-city",
      "slug": "destination-city",
      "hasCanonicalSolution": true
    },
    {
      "folder": "1441-build-an-array-with-stack-operations",
      "slug": "build-an-array-with-stack-operations",
      "hasCanonicalSolution": true
    },
    {
      "folder": "1450-number-of-students-doing-homework-at-a-given-time",
      "slug": "number-of-students-doing-homework-at-a-given-time",
      "hasCanonicalSolution": true
    },
    {
      "folder": "1464-maximum-product-of-two-elements-in-an-array",
      "slug": "maximum-product-of-two-elements-in-an-array",
      "hasCanonicalSolution": true
    },
    {
      "folder": "1470-shuffle-the-array",
      "slug": "shuffle-the-array",
      "hasCanonicalSolution": true
    },
    {
      "folder": "1480-running-sum-of-1d-array",
      "slug": "running-sum-of-1d-array",
      "hasCanonicalSolution": true
    },
    {
      "folder": "1486-xor-operation-in-an-array",
      "slug": "xor-operation-in-an-array",
      "hasCanonicalSolution": true
    },
    {
      "folder": "1496-path-crossing",
      "slug": "path-crossing",
      "hasCanonicalSolution": true
    },
    {
      "folder": "1502-can-make-arithmetic-progression-from-sequence",
      "slug": "can-make-arithmetic-progression-from-sequence",
      "hasCanonicalSolution": true
    },
    {
      "folder": "1512-number-of-good-pairs",
      "slug": "number-of-good-pairs",
      "hasCanonicalSolution": false
    },
    {
      "folder": "1528-shuffle-string",
      "slug": "shuffle-string",
      "hasCanonicalSolution": true
    },
    {
      "folder": "1534-count-good-triplets",
      "slug": "count-good-triplets",
      "hasCanonicalSolution": false
    },
    {
      "folder": "1550-three-consecutive-odds",
      "slug": "three-consecutive-odds",
      "hasCanonicalSolution": true
    },
    {
      "folder": "1588-sum-of-all-odd-length-subarrays",
      "slug": "sum-of-all-odd-length-subarrays",
      "hasCanonicalSolution": true
    },
    {
      "folder": "1636-sort-array-by-increasing-frequency",
      "slug": "sort-array-by-increasing-frequency",
      "hasCanonicalSolution": true
    },
    {
      "folder": "1662-check-if-two-string-arrays-are-equivalent",
      "slug": "check-if-two-string-arrays-are-equivalent",
      "hasCanonicalSolution": true
    },
    {
      "folder": "1672-richest-customer-wealth",
      "slug": "richest-customer-wealth",
      "hasCanonicalSolution": true
    },
    {
      "folder": "1678-goal-parser-interpretation",
      "slug": "goal-parser-interpretation",
      "hasCanonicalSolution": true
    },
    {
      "folder": "1684-count-the-number-of-consistent-strings",
      "slug": "count-the-number-of-consistent-strings",
      "hasCanonicalSolution": false
    },
    {
      "folder": "1704-determine-if-string-halves-are-alike",
      "slug": "determine-if-string-halves-are-alike",
      "hasCanonicalSolution": false
    },
    {
      "folder": "1748-sum-of-unique-elements",
      "slug": "sum-of-unique-elements",
      "hasCanonicalSolution": false
    },
    {
      "folder": "1768-merge-strings-alternately",
      "slug": "merge-strings-alternately",
      "hasCanonicalSolution": true
    },
    {
      "folder": "1773-count-items-matching-a-rule",
      "slug": "count-items-matching-a-rule",
      "hasCanonicalSolution": false
    },
    {
      "folder": "1816-truncate-sentence",
      "slug": "truncate-sentence",
      "hasCanonicalSolution": true
    },
    {
      "folder": "1822-sign-of-the-product-of-an-array",
      "slug": "sign-of-the-product-of-an-array",
      "hasCanonicalSolution": true
    },
    {
      "folder": "1832-check-if-the-sentence-is-pangram",
      "slug": "check-if-the-sentence-is-pangram",
      "hasCanonicalSolution": true
    },
    {
      "folder": "1837-sum-of-digits-in-base-k",
      "slug": "sum-of-digits-in-base-k",
      "hasCanonicalSolution": true
    },
    {
      "folder": "1859-sorting-the-sentence",
      "slug": "sorting-the-sentence",
      "hasCanonicalSolution": false
    },
    {
      "folder": "1866-number-of-ways-to-rearrange-sticks-with-k-sticks-visible",
      "slug": "number-of-ways-to-rearrange-sticks-with-k-sticks-visible",
      "hasCanonicalSolution": true
    },
    {
      "folder": "1920-build-array-from-permutation",
      "slug": "build-array-from-permutation",
      "hasCanonicalSolution": true
    },
    {
      "folder": "1929-concatenation-of-array",
      "slug": "concatenation-of-array",
      "hasCanonicalSolution": true
    },
    {
      "folder": "1935-maximum-number-of-words-you-can-type",
      "slug": "maximum-number-of-words-you-can-type",
      "hasCanonicalSolution": false
    },
    {
      "folder": "1941-check-if-all-characters-have-equal-number-of-occurrences",
      "slug": "check-if-all-characters-have-equal-number-of-occurrences",
      "hasCanonicalSolution": false
    },
    {
      "folder": "1952-three-divisors",
      "slug": "three-divisors",
      "hasCanonicalSolution": true
    },
    {
      "folder": "1967-number-of-strings-that-appear-as-substrings-in-word",
      "slug": "number-of-strings-that-appear-as-substrings-in-word",
      "hasCanonicalSolution": true
    },
    {
      "folder": "1979-find-greatest-common-divisor-of-array",
      "slug": "find-greatest-common-divisor-of-array",
      "hasCanonicalSolution": true
    },
    {
      "folder": "1995-count-special-quadruplets",
      "slug": "count-special-quadruplets",
      "hasCanonicalSolution": false
    },
    {
      "folder": "2000-reverse-prefix-of-word",
      "slug": "reverse-prefix-of-word",
      "hasCanonicalSolution": false
    },
    {
      "folder": "2006-count-number-of-pairs-with-absolute-difference-k",
      "slug": "count-number-of-pairs-with-absolute-difference-k",
      "hasCanonicalSolution": true
    },
    {
      "folder": "2011-final-value-of-variable-after-performing-operations",
      "slug": "final-value-of-variable-after-performing-operations",
      "hasCanonicalSolution": true
    },
    {
      "folder": "2032-two-out-of-three",
      "slug": "two-out-of-three",
      "hasCanonicalSolution": false
    },
    {
      "folder": "2042-check-if-numbers-are-ascending-in-a-sentence",
      "slug": "check-if-numbers-are-ascending-in-a-sentence",
      "hasCanonicalSolution": false
    },
    {
      "folder": "2085-count-common-words-with-one-occurrence",
      "slug": "count-common-words-with-one-occurrence",
      "hasCanonicalSolution": true
    },
    {
      "folder": "2095-delete-the-middle-node-of-a-linked-list",
      "slug": "delete-the-middle-node-of-a-linked-list",
      "hasCanonicalSolution": false
    },
    {
      "folder": "2108-find-first-palindromic-string-in-the-array",
      "slug": "find-first-palindromic-string-in-the-array",
      "hasCanonicalSolution": true
    },
    {
      "folder": "2114-maximum-number-of-words-found-in-sentences",
      "slug": "maximum-number-of-words-found-in-sentences",
      "hasCanonicalSolution": true
    },
    {
      "folder": "2119-a-number-after-a-double-reversal",
      "slug": "a-number-after-a-double-reversal",
      "hasCanonicalSolution": true
    },
    {
      "folder": "2124-check-if-all-as-appears-before-all-bs",
      "slug": "check-if-all-as-appears-before-all-bs",
      "hasCanonicalSolution": false
    },
    {
      "folder": "2129-capitalize-the-title",
      "slug": "capitalize-the-title",
      "hasCanonicalSolution": true
    },
    {
      "folder": "2130-maximum-twin-sum-of-a-linked-list",
      "slug": "maximum-twin-sum-of-a-linked-list",
      "hasCanonicalSolution": false
    },
    {
      "folder": "2144-minimum-cost-of-buying-candies-with-discount",
      "slug": "minimum-cost-of-buying-candies-with-discount",
      "hasCanonicalSolution": true
    },
    {
      "folder": "2160-minimum-sum-of-four-digit-number-after-splitting-digits",
      "slug": "minimum-sum-of-four-digit-number-after-splitting-digits",
      "hasCanonicalSolution": true
    },
    {
      "folder": "2161-partition-array-according-to-given-pivot",
      "slug": "partition-array-according-to-given-pivot",
      "hasCanonicalSolution": true
    },
    {
      "folder": "2169-count-operations-to-obtain-zero",
      "slug": "count-operations-to-obtain-zero",
      "hasCanonicalSolution": true
    },
    {
      "folder": "2176-count-equal-and-divisible-pairs-in-an-array",
      "slug": "count-equal-and-divisible-pairs-in-an-array",
      "hasCanonicalSolution": true
    },
    {
      "folder": "2185-counting-words-with-a-given-prefix",
      "slug": "counting-words-with-a-given-prefix",
      "hasCanonicalSolution": true
    },
    {
      "folder": "2196-create-binary-tree-from-descriptions",
      "slug": "create-binary-tree-from-descriptions",
      "hasCanonicalSolution": true
    },
    {
      "folder": "2215-find-the-difference-of-two-arrays",
      "slug": "find-the-difference-of-two-arrays",
      "hasCanonicalSolution": true
    },
    {
      "folder": "2235-add-two-integers",
      "slug": "add-two-integers",
      "hasCanonicalSolution": true
    },
    {
      "folder": "2248-intersection-of-multiple-arrays",
      "slug": "intersection-of-multiple-arrays",
      "hasCanonicalSolution": true
    },
    {
      "folder": "2309-greatest-english-letter-in-upper-and-lower-case",
      "slug": "greatest-english-letter-in-upper-and-lower-case",
      "hasCanonicalSolution": true
    },
    {
      "folder": "2315-count-asterisks",
      "slug": "count-asterisks",
      "hasCanonicalSolution": false
    },
    {
      "folder": "2367-number-of-arithmetic-triplets",
      "slug": "number-of-arithmetic-triplets",
      "hasCanonicalSolution": false
    },
    {
      "folder": "2390-removing-stars-from-a-string",
      "slug": "removing-stars-from-a-string",
      "hasCanonicalSolution": true
    },
    {
      "folder": "2396-strictly-palindromic-number",
      "slug": "strictly-palindromic-number",
      "hasCanonicalSolution": true
    },
    {
      "folder": "2413-smallest-even-multiple",
      "slug": "smallest-even-multiple",
      "hasCanonicalSolution": true
    },
    {
      "folder": "2418-sort-the-people",
      "slug": "sort-the-people",
      "hasCanonicalSolution": true
    },
    {
      "folder": "2427-number-of-common-factors",
      "slug": "number-of-common-factors",
      "hasCanonicalSolution": true
    },
    {
      "folder": "2433-find-the-original-array-of-prefix-xor",
      "slug": "find-the-original-array-of-prefix-xor",
      "hasCanonicalSolution": false
    },
    {
      "folder": "2437-number-of-valid-clock-times",
      "slug": "number-of-valid-clock-times",
      "hasCanonicalSolution": true
    },
    {
      "folder": "2441-largest-positive-integer-that-exists-with-its-negative",
      "slug": "largest-positive-integer-that-exists-with-its-negative",
      "hasCanonicalSolution": false
    },
    {
      "folder": "2465-number-of-distinct-averages",
      "slug": "number-of-distinct-averages",
      "hasCanonicalSolution": false
    },
    {
      "folder": "2469-convert-the-temperature",
      "slug": "convert-the-temperature",
      "hasCanonicalSolution": true
    },
    {
      "folder": "2481-minimum-cuts-to-divide-a-circle",
      "slug": "minimum-cuts-to-divide-a-circle",
      "hasCanonicalSolution": true
    },
    {
      "folder": "2485-find-the-pivot-integer",
      "slug": "find-the-pivot-integer",
      "hasCanonicalSolution": true
    },
    {
      "folder": "2520-count-the-digits-that-divide-a-number",
      "slug": "count-the-digits-that-divide-a-number",
      "hasCanonicalSolution": true
    },
    {
      "folder": "2523-closest-prime-numbers-in-range",
      "slug": "closest-prime-numbers-in-range",
      "hasCanonicalSolution": true
    },
    {
      "folder": "2535-difference-between-element-sum-and-digit-sum-of-an-array",
      "slug": "difference-between-element-sum-and-digit-sum-of-an-array",
      "hasCanonicalSolution": true
    },
    {
      "folder": "2540-minimum-common-value",
      "slug": "minimum-common-value",
      "hasCanonicalSolution": true
    },
    {
      "folder": "2553-separate-the-digits-in-an-array",
      "slug": "separate-the-digits-in-an-array",
      "hasCanonicalSolution": true
    },
    {
      "folder": "2574-left-and-right-sum-differences",
      "slug": "left-and-right-sum-differences",
      "hasCanonicalSolution": true
    },
    {
      "folder": "2586-count-the-number-of-vowel-strings-in-range",
      "slug": "count-the-number-of-vowel-strings-in-range",
      "hasCanonicalSolution": false
    },
    {
      "folder": "2620-counter",
      "slug": "counter",
      "hasCanonicalSolution": false
    },
    {
      "folder": "2652-sum-multiples",
      "slug": "sum-multiples",
      "hasCanonicalSolution": true
    },
    {
      "folder": "2656-maximum-sum-with-exactly-k-elements",
      "slug": "maximum-sum-with-exactly-k-elements",
      "hasCanonicalSolution": true
    },
    {
      "folder": "2657-find-the-prefix-common-array-of-two-arrays",
      "slug": "find-the-prefix-common-array-of-two-arrays",
      "hasCanonicalSolution": false
    },
    {
      "folder": "2667-create-hello-world-function",
      "slug": "create-hello-world-function",
      "hasCanonicalSolution": false
    },
    {
      "folder": "2678-number-of-senior-citizens",
      "slug": "number-of-senior-citizens",
      "hasCanonicalSolution": true
    },
    {
      "folder": "2703-return-length-of-arguments-passed",
      "slug": "return-length-of-arguments-passed",
      "hasCanonicalSolution": true
    },
    {
      "folder": "2710-remove-trailing-zeros-from-a-string",
      "slug": "remove-trailing-zeros-from-a-string",
      "hasCanonicalSolution": false
    },
    {
      "folder": "2716-minimize-string-length",
      "slug": "minimize-string-length",
      "hasCanonicalSolution": false
    },
    {
      "folder": "2733-neither-minimum-nor-maximum",
      "slug": "neither-minimum-nor-maximum",
      "hasCanonicalSolution": true
    },
    {
      "folder": "2744-find-maximum-number-of-string-pairs",
      "slug": "find-maximum-number-of-string-pairs",
      "hasCanonicalSolution": false
    },
    {
      "folder": "2769-find-the-maximum-achievable-number",
      "slug": "find-the-maximum-achievable-number",
      "hasCanonicalSolution": true
    },
    {
      "folder": "2778-sum-of-squares-of-special-elements",
      "slug": "sum-of-squares-of-special-elements",
      "hasCanonicalSolution": true
    },
    {
      "folder": "2785-sort-vowels-in-a-string",
      "slug": "sort-vowels-in-a-string",
      "hasCanonicalSolution": false
    },
    {
      "folder": "2798-number-of-employees-who-met-the-target",
      "slug": "number-of-employees-who-met-the-target",
      "hasCanonicalSolution": true
    },
    {
      "folder": "2810-faulty-keyboard",
      "slug": "faulty-keyboard",
      "hasCanonicalSolution": false
    },
    {
      "folder": "2824-count-pairs-whose-sum-is-less-than-target",
      "slug": "count-pairs-whose-sum-is-less-than-target",
      "hasCanonicalSolution": false
    },
    {
      "folder": "2828-check-if-a-string-is-an-acronym-of-words",
      "slug": "check-if-a-string-is-an-acronym-of-words",
      "hasCanonicalSolution": true
    },
    {
      "folder": "2840-check-if-strings-can-be-made-equal-with-operations-ii",
      "slug": "check-if-strings-can-be-made-equal-with-operations-ii",
      "hasCanonicalSolution": true
    },
    {
      "folder": "2843-count-symmetric-integers",
      "slug": "count-symmetric-integers",
      "hasCanonicalSolution": true
    },
    {
      "folder": "2864-maximum-odd-binary-number",
      "slug": "maximum-odd-binary-number",
      "hasCanonicalSolution": true
    },
    {
      "folder": "2894-divisible-and-non-divisible-sums-difference",
      "slug": "divisible-and-non-divisible-sums-difference",
      "hasCanonicalSolution": true
    },
    {
      "folder": "2928-distribute-candies-among-children-i",
      "slug": "distribute-candies-among-children-i",
      "hasCanonicalSolution": true
    },
    {
      "folder": "2942-find-words-containing-character",
      "slug": "find-words-containing-character",
      "hasCanonicalSolution": true
    },
    {
      "folder": "2956-find-common-elements-between-two-arrays",
      "slug": "find-common-elements-between-two-arrays",
      "hasCanonicalSolution": false
    },
    {
      "folder": "2974-minimum-number-game",
      "slug": "minimum-number-game",
      "hasCanonicalSolution": true
    },
    {
      "folder": "3005-count-elements-with-maximum-frequency",
      "slug": "count-elements-with-maximum-frequency",
      "hasCanonicalSolution": false
    },
    {
      "folder": "3019-number-of-changing-keys",
      "slug": "number-of-changing-keys",
      "hasCanonicalSolution": true
    },
    {
      "folder": "3024-type-of-triangle",
      "slug": "type-of-triangle",
      "hasCanonicalSolution": true
    },
    {
      "folder": "3110-score-of-a-string",
      "slug": "score-of-a-string",
      "hasCanonicalSolution": true
    },
    {
      "folder": "3120-count-the-number-of-special-characters-i",
      "slug": "count-the-number-of-special-characters-i",
      "hasCanonicalSolution": true
    },
    {
      "folder": "3121-count-the-number-of-special-characters-ii",
      "slug": "count-the-number-of-special-characters-ii",
      "hasCanonicalSolution": true
    },
    {
      "folder": "3136-valid-word",
      "slug": "valid-word",
      "hasCanonicalSolution": true
    },
    {
      "folder": "3146-permutation-difference-between-two-strings",
      "slug": "permutation-difference-between-two-strings",
      "hasCanonicalSolution": true
    },
    {
      "folder": "3159-find-occurrences-of-an-element-in-an-array",
      "slug": "find-occurrences-of-an-element-in-an-array",
      "hasCanonicalSolution": false
    },
    {
      "folder": "3162-find-the-number-of-good-pairs-i",
      "slug": "find-the-number-of-good-pairs-i",
      "hasCanonicalSolution": false
    },
    {
      "folder": "3168-minimum-number-of-chairs-in-a-waiting-room",
      "slug": "minimum-number-of-chairs-in-a-waiting-room",
      "hasCanonicalSolution": true
    },
    {
      "folder": "3174-clear-digits",
      "slug": "clear-digits",
      "hasCanonicalSolution": false
    },
    {
      "folder": "3190-find-minimum-operations-to-make-all-elements-divisible-by-three",
      "slug": "find-minimum-operations-to-make-all-elements-divisible-by-three",
      "hasCanonicalSolution": false
    },
    {
      "folder": "3194-minimum-average-of-smallest-and-largest-elements",
      "slug": "minimum-average-of-smallest-and-largest-elements",
      "hasCanonicalSolution": true
    },
    {
      "folder": "3210-find-the-encrypted-string",
      "slug": "find-the-encrypted-string",
      "hasCanonicalSolution": true
    },
    {
      "folder": "3232-find-if-digit-game-can-be-won",
      "slug": "find-if-digit-game-can-be-won",
      "hasCanonicalSolution": true
    },
    {
      "folder": "3270-find-the-key-of-the-numbers",
      "slug": "find-the-key-of-the-numbers",
      "hasCanonicalSolution": true
    },
    {
      "folder": "3274-check-if-two-chessboard-squares-have-the-same-color",
      "slug": "check-if-two-chessboard-squares-have-the-same-color",
      "hasCanonicalSolution": true
    },
    {
      "folder": "3280-convert-date-to-binary",
      "slug": "convert-date-to-binary",
      "hasCanonicalSolution": true
    },
    {
      "folder": "3289-the-two-sneaky-numbers-of-digitville",
      "slug": "the-two-sneaky-numbers-of-digitville",
      "hasCanonicalSolution": true
    },
    {
      "folder": "3300-minimum-element-after-replacement-with-digit-sum",
      "slug": "minimum-element-after-replacement-with-digit-sum",
      "hasCanonicalSolution": true
    },
    {
      "folder": "3370-smallest-number-with-all-set-bits",
      "slug": "smallest-number-with-all-set-bits",
      "hasCanonicalSolution": true
    },
    {
      "folder": "3461-check-if-digits-are-equal-in-string-after-operations-i",
      "slug": "check-if-digits-are-equal-in-string-after-operations-i",
      "hasCanonicalSolution": false
    },
    {
      "folder": "3467-transform-array-by-parity",
      "slug": "transform-array-by-parity",
      "hasCanonicalSolution": false
    },
    {
      "folder": "3492-maximum-containers-on-a-ship",
      "slug": "maximum-containers-on-a-ship",
      "hasCanonicalSolution": true
    },
    {
      "folder": "3498-reverse-degree-of-a-string",
      "slug": "reverse-degree-of-a-string",
      "hasCanonicalSolution": true
    },
    {
      "folder": "3512-minimum-operations-to-make-array-sum-divisible-by-k",
      "slug": "minimum-operations-to-make-array-sum-divisible-by-k",
      "hasCanonicalSolution": true
    },
    {
      "folder": "3516-find-closest-person",
      "slug": "find-closest-person",
      "hasCanonicalSolution": true
    },
    {
      "folder": "3527-find-the-most-common-response",
      "slug": "find-the-most-common-response",
      "hasCanonicalSolution": false
    },
    {
      "folder": "3541-find-most-frequent-vowel-and-consonant",
      "slug": "find-most-frequent-vowel-and-consonant",
      "hasCanonicalSolution": true
    },
    {
      "folder": "3558-number-of-ways-to-assign-edge-weights-i",
      "slug": "number-of-ways-to-assign-edge-weights-i",
      "hasCanonicalSolution": true
    },
    {
      "folder": "3559-number-of-ways-to-assign-edge-weights-ii",
      "slug": "number-of-ways-to-assign-edge-weights-ii",
      "hasCanonicalSolution": true
    },
    {
      "folder": "3612-process-string-with-special-operations-i",
      "slug": "process-string-with-special-operations-i",
      "hasCanonicalSolution": false
    },
    {
      "folder": "3614-process-string-with-special-operations-ii",
      "slug": "process-string-with-special-operations-ii",
      "hasCanonicalSolution": false
    },
    {
      "folder": "3622-check-divisibility-by-digit-sum-and-product",
      "slug": "check-divisibility-by-digit-sum-and-product",
      "hasCanonicalSolution": true
    },
    {
      "folder": "3633-earliest-finish-time-for-land-and-water-rides-i",
      "slug": "earliest-finish-time-for-land-and-water-rides-i",
      "hasCanonicalSolution": true
    },
    {
      "folder": "3635-earliest-finish-time-for-land-and-water-rides-ii",
      "slug": "earliest-finish-time-for-land-and-water-rides-ii",
      "hasCanonicalSolution": true
    },
    {
      "folder": "3668-restore-finishing-order",
      "slug": "restore-finishing-order",
      "hasCanonicalSolution": true
    },
    {
      "folder": "3684-maximize-sum-of-at-most-k-distinct-elements",
      "slug": "maximize-sum-of-at-most-k-distinct-elements",
      "hasCanonicalSolution": false
    },
    {
      "folder": "3689-maximum-total-subarray-value-i",
      "slug": "maximum-total-subarray-value-i",
      "hasCanonicalSolution": true
    },
    {
      "folder": "3691-maximum-total-subarray-value-ii",
      "slug": "maximum-total-subarray-value-ii",
      "hasCanonicalSolution": true
    },
    {
      "folder": "3701-compute-alternating-sum",
      "slug": "compute-alternating-sum",
      "hasCanonicalSolution": true
    },
    {
      "folder": "3712-sum-of-elements-with-frequency-divisible-by-k",
      "slug": "sum-of-elements-with-frequency-divisible-by-k",
      "hasCanonicalSolution": false
    },
    {
      "folder": "3731-find-missing-elements",
      "slug": "find-missing-elements",
      "hasCanonicalSolution": false
    },
    {
      "folder": "3751-total-waviness-of-numbers-in-range-i",
      "slug": "total-waviness-of-numbers-in-range-i",
      "hasCanonicalSolution": true
    },
    {
      "folder": "3753-total-waviness-of-numbers-in-range-ii",
      "slug": "total-waviness-of-numbers-in-range-ii",
      "hasCanonicalSolution": true
    },
    {
      "folder": "3760-maximum-substrings-with-distinct-start",
      "slug": "maximum-substrings-with-distinct-start",
      "hasCanonicalSolution": true
    },
    {
      "folder": "3783-mirror-distance-of-an-integer",
      "slug": "mirror-distance-of-an-integer",
      "hasCanonicalSolution": true
    },
    {
      "folder": "3794-reverse-string-prefix",
      "slug": "reverse-string-prefix",
      "hasCanonicalSolution": true
    },
    {
      "folder": "3803-count-residue-prefixes",
      "slug": "count-residue-prefixes",
      "hasCanonicalSolution": false
    },
    {
      "folder": "3833-count-dominant-indices",
      "slug": "count-dominant-indices",
      "hasCanonicalSolution": false
    },
    {
      "folder": "3838-weighted-word-mapping",
      "slug": "weighted-word-mapping",
      "hasCanonicalSolution": true
    },
    {
      "folder": "3884-first-matching-character-from-both-ends",
      "slug": "first-matching-character-from-both-ends",
      "hasCanonicalSolution": false
    },
    {
      "folder": "3895-count-digit-appearances",
      "slug": "count-digit-appearances",
      "hasCanonicalSolution": true
    },
    {
      "folder": "3898-find-the-degree-of-each-vertex",
      "slug": "find-the-degree-of-each-vertex",
      "hasCanonicalSolution": true
    },
    {
      "folder": "3925-concatenate-array-with-reverse",
      "slug": "concatenate-array-with-reverse",
      "hasCanonicalSolution": true
    },
    {
      "folder": "3936-minimum-swaps-to-move-zeros-to-end",
      "slug": "minimum-swaps-to-move-zeros-to-end",
      "hasCanonicalSolution": false
    },
    {
      "folder": "3941-password-strength",
      "slug": "password-strength",
      "hasCanonicalSolution": true
    },
    {
      "folder": "3945-digit-frequency-score",
      "slug": "digit-frequency-score",
      "hasCanonicalSolution": true
    }
  ]
}
